pytunics/__init__.py
pytunics/laser.py
pytunics-1.0.5.dist-info/LICENSE
pytunics-1.0.5.dist-info/METADATA
pytunics-1.0.5.dist-info/WHEEL
pytunics-1.0.5.dist-info/top_level.txt
pytunics-1.0.5.dist-info/RECORD
