Metadata-Version: 2.1
Name: pytunics
Version: 1.0.5
Summary: package with main method for laser control
Home-page: https://gitlab.xlim.fr/vasko/Tunics-Laser-control-python
Author: Kostiantyn Vasko
Author-email: kostiantyn.vasko@nure.ua
License: UNKNOWN
Project-URL: Bug Tracker, https://gitlab.xlim.fr/vasko/Tunics-Laser-control-python/issues
Platform: UNKNOWN
Classifier: Programming Language :: Python :: 3
Classifier: License :: OSI Approved :: MIT License
Classifier: Operating System :: Microsoft :: Windows :: Windows 10
Requires-Python: >=3.8
License-File: LICENSE
